{
"meta":{"test_sets":[],"test_metrics":[],"learn_metrics":[{"best_value":"Min","name":"RMSE"}],"launch_mode":"Train","parameters":"","iteration_count":100,"learn_sets":["learn"],"name":"experiment"},
"iterations":[
{"learn":[14.005006],"iteration":0,"passed_time":0.0006383294644,"remaining_time":0.06319461697},
{"learn":[13.14441192],"iteration":1,"passed_time":0.001194750757,"remaining_time":0.05854278712},
{"learn":[12.34258257],"iteration":2,"passed_time":0.001698758612,"remaining_time":0.05492652845},
{"learn":[11.64527793],"iteration":3,"passed_time":0.002108054893,"remaining_time":0.05059331743},
{"learn":[11.02766183],"iteration":4,"passed_time":0.002615850318,"remaining_time":0.04970115604},
{"learn":[10.43485794],"iteration":5,"passed_time":0.003105799185,"remaining_time":0.04865752056},
{"learn":[9.890641275],"iteration":6,"passed_time":0.003674323978,"remaining_time":0.04881601857},
{"learn":[9.492161212],"iteration":7,"passed_time":0.004199122214,"remaining_time":0.04828990546},
{"learn":[9.105082953],"iteration":8,"passed_time":0.004724225983,"remaining_time":0.04776717383},
{"learn":[8.674157135],"iteration":9,"passed_time":0.005218684253,"remaining_time":0.04696815827},
{"learn":[8.341743544],"iteration":10,"passed_time":0.005710817199,"remaining_time":0.04620570279},
{"learn":[8.049372916],"iteration":11,"passed_time":0.006260931573,"remaining_time":0.0459134982},
{"learn":[7.757318612],"iteration":12,"passed_time":0.006799941191,"remaining_time":0.04550729874},
{"learn":[7.522206899],"iteration":13,"passed_time":0.007289836534,"remaining_time":0.04478042442},
{"learn":[7.297756655],"iteration":14,"passed_time":0.007790319234,"remaining_time":0.04414514233},
{"learn":[7.088359431],"iteration":15,"passed_time":0.008290587838,"remaining_time":0.04352558615},
{"learn":[6.882113791],"iteration":16,"passed_time":0.008905131431,"remaining_time":0.04347799464},
{"learn":[6.704728832],"iteration":17,"passed_time":0.009479292606,"remaining_time":0.0431834441},
{"learn":[6.563881962],"iteration":18,"passed_time":0.00997973888,"remaining_time":0.04254520259},
{"learn":[6.418790279],"iteration":19,"passed_time":0.01050046148,"remaining_time":0.04200184593},
{"learn":[6.315756953],"iteration":20,"passed_time":0.01098422014,"remaining_time":0.04132159006},
{"learn":[6.210157751],"iteration":21,"passed_time":0.01147346874,"remaining_time":0.04067866188},
{"learn":[6.115058449],"iteration":22,"passed_time":0.01196934837,"remaining_time":0.0400712967},
{"learn":[6.014819884],"iteration":23,"passed_time":0.0124557639,"remaining_time":0.03944325236},
{"learn":[5.93117229],"iteration":24,"passed_time":0.01294279125,"remaining_time":0.03882837374},
{"learn":[5.844857622],"iteration":25,"passed_time":0.01342697215,"remaining_time":0.03821522843},
{"learn":[5.771145213],"iteration":26,"passed_time":0.01390290143,"remaining_time":0.03758932609},
{"learn":[5.704018229],"iteration":27,"passed_time":0.01440363911,"remaining_time":0.03703792915},
{"learn":[5.665806474],"iteration":28,"passed_time":0.01488389121,"remaining_time":0.03643987157},
{"learn":[5.616500369],"iteration":29,"passed_time":0.01537917315,"remaining_time":0.03588473735},
{"learn":[5.558023666],"iteration":30,"passed_time":0.01587000516,"remaining_time":0.03532355988},
{"learn":[5.510080976],"iteration":31,"passed_time":0.01638831286,"remaining_time":0.03482516484},
{"learn":[5.468747792],"iteration":32,"passed_time":0.01688973075,"remaining_time":0.03429127152},
{"learn":[5.429275534],"iteration":33,"passed_time":0.01738517178,"remaining_time":0.0337476864},
{"learn":[5.402117324],"iteration":34,"passed_time":0.01789063593,"remaining_time":0.03322546674},
{"learn":[5.367635151],"iteration":35,"passed_time":0.01867707875,"remaining_time":0.03320369555},
{"learn":[5.345181232],"iteration":36,"passed_time":0.01925050657,"remaining_time":0.03277788956},
{"learn":[5.319151269],"iteration":37,"passed_time":0.01978934669,"remaining_time":0.03228788145},
{"learn":[5.296134146],"iteration":38,"passed_time":0.02027957731,"remaining_time":0.03171933886},
{"learn":[5.269629003],"iteration":39,"passed_time":0.02075505683,"remaining_time":0.03113258525},
{"learn":[5.251147059],"iteration":40,"passed_time":0.02123752348,"remaining_time":0.03056131428},
{"learn":[5.248003302],"iteration":41,"passed_time":0.02144451665,"remaining_time":0.02961385632},
{"learn":[5.232376509],"iteration":42,"passed_time":0.02191177874,"remaining_time":0.02904584624},
{"learn":[5.213524255],"iteration":43,"passed_time":0.02238821204,"remaining_time":0.02849408805},
{"learn":[5.189691584],"iteration":44,"passed_time":0.02287307166,"remaining_time":0.02795597648},
{"learn":[5.166052198],"iteration":45,"passed_time":0.02337277157,"remaining_time":0.02743760141},
{"learn":[5.140406659],"iteration":46,"passed_time":0.0238689835,"remaining_time":0.02691608778},
{"learn":[5.118929684],"iteration":47,"passed_time":0.0244050203,"remaining_time":0.02643877199},
{"learn":[5.108792602],"iteration":48,"passed_time":0.02502227541,"remaining_time":0.02604359277},
{"learn":[5.098141225],"iteration":49,"passed_time":0.02554327492,"remaining_time":0.02554327492},
{"learn":[5.085926393],"iteration":50,"passed_time":0.0260309059,"remaining_time":0.02501008606},
{"learn":[5.067816804],"iteration":51,"passed_time":0.02655146161,"remaining_time":0.02450904149},
{"learn":[5.049834901],"iteration":52,"passed_time":0.02704204013,"remaining_time":0.0239806771},
{"learn":[5.03838627],"iteration":53,"passed_time":0.02769412193,"remaining_time":0.02359128905},
{"learn":[5.033534248],"iteration":54,"passed_time":0.02806725751,"remaining_time":0.02296411978},
{"learn":[5.023726885],"iteration":55,"passed_time":0.02857427311,"remaining_time":0.02245121459},
{"learn":[5.01290392],"iteration":56,"passed_time":0.02909418133,"remaining_time":0.02194824206},
{"learn":[5.005569127],"iteration":57,"passed_time":0.02957159813,"remaining_time":0.02141391589},
{"learn":[4.989969032],"iteration":58,"passed_time":0.0300680591,"remaining_time":0.02089475293},
{"learn":[4.976762446],"iteration":59,"passed_time":0.03054731802,"remaining_time":0.02036487868},
{"learn":[4.967222715],"iteration":60,"passed_time":0.03104465432,"remaining_time":0.01984822162},
{"learn":[4.954407599],"iteration":61,"passed_time":0.03159097295,"remaining_time":0.01936220923},
{"learn":[4.942125056],"iteration":62,"passed_time":0.03209607284,"remaining_time":0.01885007453},
{"learn":[4.930230716],"iteration":63,"passed_time":0.03267457467,"remaining_time":0.01837944825},
{"learn":[4.921695642],"iteration":64,"passed_time":0.03324547162,"remaining_time":0.01790140779},
{"learn":[4.906405625],"iteration":65,"passed_time":0.03380581355,"remaining_time":0.01741511607},
{"learn":[4.894330248],"iteration":66,"passed_time":0.03433331029,"remaining_time":0.01691043641},
{"learn":[4.88211557],"iteration":67,"passed_time":0.0348524714,"remaining_time":0.01640116301},
{"learn":[4.877946398],"iteration":68,"passed_time":0.03535562213,"remaining_time":0.01588440994},
{"learn":[4.863182126],"iteration":69,"passed_time":0.03584071443,"remaining_time":0.01536030618},
{"learn":[4.84646533],"iteration":70,"passed_time":0.03631129353,"remaining_time":0.01483137341},
{"learn":[4.838014752],"iteration":71,"passed_time":0.03681398187,"remaining_time":0.0143165485},
{"learn":[4.82981137],"iteration":72,"passed_time":0.03731200692,"remaining_time":0.01380033133},
{"learn":[4.817094767],"iteration":73,"passed_time":0.03777845278,"remaining_time":0.01327351044},
{"learn":[4.808314151],"iteration":74,"passed_time":0.03824514024,"remaining_time":0.01274838008},
{"learn":[4.796235023],"iteration":75,"passed_time":0.03885260825,"remaining_time":0.01226924471},
{"learn":[4.784434534],"iteration":76,"passed_time":0.03937036881,"remaining_time":0.01175998029},
{"learn":[4.774402487],"iteration":77,"passed_time":0.03987342661,"remaining_time":0.0112463511},
{"learn":[4.76731896],"iteration":78,"passed_time":0.0403676128,"remaining_time":0.01073063125},
{"learn":[4.75934113],"iteration":79,"passed_time":0.04084659741,"remaining_time":0.01021164935},
{"learn":[4.754106378],"iteration":80,"passed_time":0.04137129046,"remaining_time":0.009704376775},
{"learn":[4.744002932],"iteration":81,"passed_time":0.04186508191,"remaining_time":0.009189896029},
{"learn":[4.731700554],"iteration":82,"passed_time":0.04240681085,"remaining_time":0.008685732342},
{"learn":[4.723284153],"iteration":83,"passed_time":0.04288777585,"remaining_time":0.008169100162},
{"learn":[4.712232782],"iteration":84,"passed_time":0.04338160595,"remaining_time":0.007655577521},
{"learn":[4.703046867],"iteration":85,"passed_time":0.0438575278,"remaining_time":0.007139597549},
{"learn":[4.698601855],"iteration":86,"passed_time":0.04433735987,"remaining_time":0.00662512274},
{"learn":[4.692429407],"iteration":87,"passed_time":0.04481555278,"remaining_time":0.006111211742},
{"learn":[4.675027364],"iteration":88,"passed_time":0.04528915227,"remaining_time":0.005597535674},
{"learn":[4.662368584],"iteration":89,"passed_time":0.04576544358,"remaining_time":0.005085049287},
{"learn":[4.646206172],"iteration":90,"passed_time":0.04646255622,"remaining_time":0.004595197868},
{"learn":[4.641245848],"iteration":91,"passed_time":0.0470507433,"remaining_time":0.004091368983},
{"learn":[4.633900435],"iteration":92,"passed_time":0.04756036821,"remaining_time":0.003579812661},
{"learn":[4.624738236],"iteration":93,"passed_time":0.04808075889,"remaining_time":0.00306898461},
{"learn":[4.612798287],"iteration":94,"passed_time":0.04856878014,"remaining_time":0.002556251587},
{"learn":[4.605222001],"iteration":95,"passed_time":0.04909984739,"remaining_time":0.002045826974},
{"learn":[4.601725912],"iteration":96,"passed_time":0.0495832455,"remaining_time":0.001533502438},
{"learn":[4.59722371],"iteration":97,"passed_time":0.05006794975,"remaining_time":0.001021794893},
{"learn":[4.580235665],"iteration":98,"passed_time":0.05059548961,"remaining_time":0.0005110655516},
{"learn":[4.57591791],"iteration":99,"passed_time":0.05107332123,"remaining_time":0}
]}